README.rst
setup.py
gtfe/__init__.py
gtfe.egg-info/PKG-INFO
gtfe.egg-info/SOURCES.txt
gtfe.egg-info/dependency_links.txt
gtfe.egg-info/requires.txt
gtfe.egg-info/top_level.txt